LICENSE
README.md
setup.py
paystackapi/__init__.py
paystackapi/base.py
paystackapi/bulkcharge.py
paystackapi/charge.py
paystackapi/cpanel.py
paystackapi/customer.py
paystackapi/invoice.py
paystackapi/misc.py
paystackapi/page.py
paystackapi/paystack.py
paystackapi/plan.py
paystackapi/product.py
paystackapi/refund.py
paystackapi/settlement.py
paystackapi/subaccount.py
paystackapi/subscription.py
paystackapi/tcontrol.py
paystackapi/transaction.py
paystackapi/transaction_split.py
paystackapi/transfer.py
paystackapi/trecipient.py
paystackapi/verification.py
paystackapi.egg-info/PKG-INFO
paystackapi.egg-info/SOURCES.txt
paystackapi.egg-info/dependency_links.txt
paystackapi.egg-info/requires.txt
paystackapi.egg-info/top_level.txt
paystackapi/tests/__init__.py
paystackapi/tests/base_test_case.py
paystackapi/tests/test_base.py
paystackapi/tests/test_bulkcharge.py
paystackapi/tests/test_charge.py
paystackapi/tests/test_cpanel.py
paystackapi/tests/test_customer.py
paystackapi/tests/test_invoice.py
paystackapi/tests/test_misc.py
paystackapi/tests/test_page.py
paystackapi/tests/test_paystack.py
paystackapi/tests/test_plan.py
paystackapi/tests/test_product.py
paystackapi/tests/test_refund.py
paystackapi/tests/test_settlement.py
paystackapi/tests/test_subaccount.py
paystackapi/tests/test_subscription.py
paystackapi/tests/test_tcontrol.py
paystackapi/tests/test_transaction.py
paystackapi/tests/test_transaction_split.py
paystackapi/tests/test_transfer.py
paystackapi/tests/test_trecipient.py
paystackapi/tests/test_verification.py