Metadata-Version: 2.1
Name: paystackapi
Version: 2.1.0
Summary: A python library to consume Paystack API
Home-page: https://github.com/andela-sjames/paystack-python
Author: Samuel James and Issa Jubril
Author-email: samuelvarejames@gmail.com
License: MIT
Keywords: paystack python library
Platform: UNKNOWN
Classifier: Development Status :: 4 - Beta
Classifier: Intended Audience :: Developers
Classifier: License :: OSI Approved :: MIT License
Classifier: Programming Language :: Python :: 3
Classifier: Programming Language :: Python :: 3.6
Provides-Extra: test
License-File: LICENSE
